AUTHORS.txt
Changelog
LICENSE
MANIFEST.in
README.rst
setup.cfg
setup.py
neomodel_serializer/__init__.py
neomodel_serializer/serializers.py
neomodel_serializer.egg-info/PKG-INFO
neomodel_serializer.egg-info/SOURCES.txt
neomodel_serializer.egg-info/dependency_links.txt
neomodel_serializer.egg-info/requires.txt
neomodel_serializer.egg-info/top_level.txt
neomodel_serializer.egg-info/zip-safe