Metadata-Version: 1.1
Name: neomodel-serializer
Version: 0.0.1.dev2
Summary: Serialize neomodels
Home-page: http://github.com/efagerberg/neomodel-serializer
Author: Evan Fagerberg
Author-email: adioevan@gmail.com
License: MIT
Keywords: neo4j neomodel serializer
Platform: UNKNOWN
Classifier: Development Status :: 2 - Pre-Alpha
Classifier: Intended Audience :: Developers
Classifier: Operating System :: OS Independent
Classifier: License :: OSI Approved :: MIT License
Classifier: Programming Language :: Python
Classifier: Topic :: Software Development :: Libraries :: Python Modules
Classifier: Programming Language :: Python :: 2.7
Classifier: Programming Language :: Python :: 3.3
Classifier: Programming Language :: Python :: 3.4
Classifier: Programming Language :: Python :: 3.5
Classifier: Programming Language :: Python :: 3.6
Classifier: Topic :: Database
